colav_protobuf/__init__.py
colav_protobuf/agentUpdate_pb2.py
colav_protobuf/automatonOutput_pb2.py
colav_protobuf/collisionMetrics_pb2.py
colav_protobuf/controllerFeedback_pb2.py
colav_protobuf/mapMetaData_pb2.py
colav_protobuf/missionRequest_pb2.py
colav_protobuf/missionResponse_pb2.py
colav_protobuf/obstaclesUpdate_pb2.py
colav_protobuf/unsafeSet_pb2.py
colav_protobuf/examples/__init__.py
colav_protobuf/examples/agent_update.py
colav_protobuf/examples/controller_feedback.py
colav_protobuf/examples/mission_request.py
colav_protobuf/examples/mission_response.py
colav_protobuf/examples/obstacles_update.py
colav_protobuf/examples/unsafe_set.py
colav_protobuf-0.2.4.dist-info/METADATA
colav_protobuf-0.2.4.dist-info/WHEEL
colav_protobuf-0.2.4.dist-info/licenses/LICENSE
colav_protobuf-0.2.4.dist-info/RECORD
