Metadata-Version: 2.4
Name: colav-protobuf
Version: 0.2.4
Summary: A Python package for importing and working with COLAV Protobuf message types, including mission requests, agent updates, obstacles updates, and controller feedback.
Project-URL: Documentation, https://github.com/RyanMcKeeQUB/colav_protobuf/blob/main/README.md
Project-URL: Issues, https://github.com/RyanMcKeeQUB/colav_protobuf/issues
Project-URL: Source, https://github.com/RyanMcKeeQUB/colav_protobuf
Author-email: Ryan <r.mckee@qub.ac.uk>
License: MIT License
License-File: LICENSE
Classifier: Development Status :: 4 - Beta
Classifier: Programming Language :: Python
Classifier: Programming Language :: Python :: 3.8
Classifier: Programming Language :: Python :: 3.9
Classifier: Programming Language :: Python :: 3.10
Classifier: Programming Language :: Python :: 3.11
Classifier: Programming Language :: Python :: 3.12
Classifier: Programming Language :: Python :: Implementation :: CPython
Classifier: Programming Language :: Python :: Implementation :: PyPy
Requires-Dist: hatch
Requires-Dist: lark
Requires-Dist: protobuf<=3.20.1
Requires-Dist: pyyaml
